{"mdPyLqZ4u21oBaVVuPcZdQ==":"background1.jpg","BQIRvUQLYjhmFfntSDdcZw==":"7.png","fKw/fwtDXD+as2GqL9aXSQ==":"6.png","II1wCfUuzrWahTOzPOsqEA==":"5.png","brA4svJmSQXTK2t7N1dNSw==":"8.png","I3dpCgo5h4HeghoXzxai2w==":"background3.jpg","eSS3lIvn75O3ZmNDx2EwkQ==":"10.png","C+g9Smy06k/ApM3KU74saw==":"1.png","Z2gLhK6rt3chbaubZ9oCDw==":"05.jpg","n263FFQFI/2UWaTr1cAPkA==":"06.jpg","ijGjBh/Hf8w/gqMb6w3IXQ==":"07.jpg","g5htbaA7COm4CJqOn1/3Sw==":"10.jpg","PrQgSBsmBbwoIF1oHTXZ4A==":"09.jpg","3FBkTzIhIM87imxt3iXlQw==":"08.jpg","kijV/HxDegIn7Vtb0qNOVw==":"02.jpg","PfV0tuRPCaNdJL4PdqcLUg==":"01.jpg","wMkX2X7txLbVGSAJxNmOeQ==":"04.jpg","Mem5Uea9TUpxshpe7/sE7Q==":"03.jpg","6aAFCmHTeSljdApIkgBC+A==":"blob4.svg","CHZkeRfYu+6p+hONBXIYPg==":"12.png","JcaHe6WjI7KIqpNiq2Hy5w==":"background2.jpg","NjkHKxnPMCrtT1T+/IVmtQ==":"cover1-1920x1280.jpg","/EqVVdxXZlmu3QVn0gXW4A==":"mbr-122x81.png","2RW9QIQSjxa8dC967czx7A==":"mbr-182x201.png","az4BtWIgLpNvDcTyGaG+VA==":"mbr-110x118.png","flsyHzLKDJfR9BbbQB2JKQ==":"cover1-1920x1280.jpeg","UVMPriqU35miinPOEKIvdw==":"mbr-114x59.jpg","74pH4r175Z0qUAsKGN8dVw==":"mbr-236x167.png","8cZ9hy544QVbiHiphuXgZw==":"mbr-1920x1308.png","qJXpi0P3vxkCqeGs7dSE0Q==":"mbr-162x108.jpg","TDjZrE9rqO/+Zi78WzprSg==":"mbr-466x262.png","eFCU3eYf3YiDBD45zympLw==":"mbr-466x466.png","ztXxdZIvPvar5D1v4Qz5jw==":"mbr-466x383.png","6mGt3QHu8Z12/hhrbwlDVQ==":"mbr-1-466x262.png","sDQ5zmrLzL8kEbaBs+tdpg==":"mbr-324x279.jpg","76X+R5RzBzDexDFhEU7ZQQ==":"mbr-1080x1786.png","dKiirqYSbQao6zPz4/vz9g==":"mbr-1080x1080.png","wiHfeaLW9zW+Pu+8tuprWw==":"mbr-1080x1027.png","OllA0oDXlFyILqo8xhURwg==":"mbr-1080x608.jpg","IPHHRN+p7xsfyhjNFqURdw==":"mbr-1080x1170.png","maa+ZUr7+6FkcAa1L6e+HQ==":"mbr-1080x720.png","gZN+MzJFtE/QdwMqLIDyfA==":"mbr-1080x540.png","TxbdyfQNb0iA+aXi6Tgm5g==":"mbr-1080x810.jpg","he4tMbU6xD3Iu/6cpUwI2Q==":"mmu-400x400.jpg","mi3ETcU3EvdSy8/PEF7iLw==":"mbr-1920x1357.png","HR9v5gE4oAwZ5FZmXez13Q==":"kisspng-manchester-metropolitan-university-business-school-5b115f28720e40.7653388215278651284672-700x700.jpg","fof1P2D5ngV2RfArElCnBQ==":"kisspng-manchester-metropolitan-university-business-school-5b115f28720e40.7653388215278651284672-700x700.jpeg","namUpdhINkOttM8ytobs5w==":"kisspng-manchester-metropolitan-university-business-school-5b115f28720e40.7653388215278651284672-1-700x700.jpeg","Hx0+U07zTLTMJb42hzuCQA==":"mmu-logo-png-2-700x849.png","5876QD26SifPIo/P8W4cJw==":"mmu-logo-png-2-700x850.png","kRTtCReDqNsRLkblh+hS8A==":"mmu-logo-png-2-468x568.png","acH7AZWA7XCvWWrhX9g35w==":"mmu-logo1-png-2-230x280.png","3m6xackDCbjbRdVEh9u+Xg==":"1mmu_logo-700x700.jpg","GQTzNz3ZMzoUbpDvrx/fbw==":"ncop%20logo%20200%20(1)-200x200.jpg","eOwp99jn8q35YmjJWSYE8w==":"spalding-224x225.jpg","w6E6HY02u7ul8urAOS2vnw==":"carres-225x225.png","DkJ/UTfubJRGwQlD9pRSbg==":"cgs_badge-150x201.jpg","o92IdC1Aj9z4eviALkDzYQ==":"spaldinggrammarschool.gif","5dMyKWE4XRn5nodmiG5giA==":"1spalding-150x150.png","ADIQMrZOLkXrvDQv9AdhZw==":"logo-118x118.png","xCzdFop7iKmXq7iIUvhOxA==":"logo-30x30.png","GSehjxlGH6bzZDeHoaKetw==":"steveoakes-480x480.png","QCa2bn/gBWmoULDSoaBjTg==":"square_martin_griffin-450x450.jpg","UNpvUalBjENmtxSl6ZgiVQ==":"tonyd-546x532.jpg","xClUGy/zqt3e91fiSZo4BQ==":"tonyd-546x532.jpeg","o7MefrcCAgwoU/na8gFq7g==":"stumind-534x757.jpg","ZTOsPcCyM35Te30+csxESQ==":"alevelmind-389x500.jpg","AcPGWortSTqTW1YjQZdM8g==":"stumind-534x757.jpeg","9+bppHkPtu/bwPCTpVuW+Q==":"gcsemind-534x679.jpg","4wfxeaDQC3JmsCU/1ZURXg==":"gcsework-400x566.jpg","ydB2CFuCnWKd6GiO/kO2pQ==":"alevel%20workbook-299x374.png","Fq8ouEYVUrTFB32PDXVNEA==":"spaldinggrammarschool.png","FxWUU7wRxT5TFetBJBttAQ==":"spalding2-44x44.png","7yUhYJqWz+hU9ho/hSHW6w==":"spalding22-265x247.png","atM6kshniWkkDqyyUfULIQ==":"22spalding-205x197.png","BNVg8/mUXJMih20AVlbOUQ==":"ncop-226x197.jpg","hlSQrUTDzmW+gT36yk4P+Q==":"ncop-217x124.jpg","FsbdohKtozcbipNjG+QBEg==":"ncop-279x243.jpg","5pn64V6le4bAq8AUPf4ZRA==":"ncop-275x240.jpg","Q3JE/DUEGVUlzB1Fxf12gg==":"ncop-235x205.jpg","PorHGFl0vKYjfIi6u6s/0Q==":"ncop-235x205.jpeg","U2Bvb1APl5dh2yjlKwUYdg==":"ncop-213x186.jpg","89JTbZooABQSLS7IgOuqeg==":"1mmu_logo-300x300.jpg","K/IV/pgQ/qXRCUQ/Mwnfdg==":"tonyd-1-546x532.jpeg","SUXVc5rqeHN34SmvM2ubCw==":"square_martin_griffin-450x450.jpeg","wOkGhe6aHEGCTnEbZ5YzYA==":"tonyd-2-546x532.jpeg","+YhgKtamSnzMEP3dy7vocQ==":"tonyd-3-546x532.jpeg","FC+vpxUXWJe9TZ3Ax9/mWQ==":"tonyd-4-546x532.jpeg","0CA29NLaGUOxCfiNdBHkuw==":"tonyd-5-546x532.jpeg","Aqeh5i5dDEDTRhQbibHgcA==":"tonyd-6-546x532.jpeg","Bwsnu3LRATeIiriBCmUb8g==":"square_martin_griffin-1-450x450.jpeg","/F8WMITMc126W97eWdTyGA==":"steveoakes-1-480x480.png","lK53aEIv1OG0RdsgQNFyjQ==":"steveoakes-2-480x480.png","7oQDXMlCueLK4F+mAbijcw==":"square_martin_griffin-2-450x450.jpeg","y8VTKsc4ThqOqrNP+vv3PQ==":"tonyd-7-546x532.jpeg","IfEYx4/kx94Ws4UgPhsThQ==":"annotation%202020-06-29%20225708-1080x501.png","uUrpHcCLa3OQ9dkLBmsMrg==":"mbr-1-466x383.png","/OEfQv4Q0w9WGOMT5NmLOw==":"mbr-2-466x262.png","9hYgS1Br1sHudQrlCkYg7w==":"mbr-1-466x466.png","IPXWQk7qlB5fGGYdD7am0w==":"mbr-324x279.jpeg","ER0nubpHhZFnipqzWdWecw==":"purple%20brain-936x702.png","/3iCnNuZ5hRRapUQnE/R4g==":"481-4814672_gems-world-academy-gems-world-academy-dubai-logo-240x94.png","itqIAOxiQo3ibqEimYeIRA==":"belfast_metropolitan_college_logo-240x240.jpg","tv8h1XK0CVHf7vGICqEDVA==":"ark-walworth-academy-southwark-london-240x240.jpg","7RUJSSznpvl0C/iDh7tnVw==":"ncc-240x74.png","vijzMfmHfICeMAhpDq4c9w==":"481-4814672_gems-world-academy-gems-world-academy-dubai-logo-1-240x94.png","MnIm8RA7ypGhswNwqp5V5w==":"dubai_british_school_-_official_logo-240x125.jpg","+QRX/FTKuHwxHmdAKYM3IA==":"cheshirecoll-240x240.png","PAV2YQKLdDq9yF6bkVDxZg==":"mbr-466x466.jpg","aaEJ92uP+SfwZi+DgY58sw==":"mbr-466x466.jpeg","/cR1kYJLQlrJtnvmvZnqMA==":"mbr-1-324x279.jpeg","wVDxf06W29nmGd2uYSB34w==":"mbr-1-466x466.jpeg","4CYZxkeMNwfO53HkwG0tLg==":"mbr-2-466x466.jpeg","nU65Wfx57cM9SnQSA9QCQw==":"mbr-2-466x383.png","9SiDcL5igALIFTgMALnPPw==":"mbr-3-466x466.jpeg","h/jOwJII/6ZLnH+YRatCNg==":"belfast_metropolitan_college_logo-240x240.jpeg","D7oV45hV46qu2EJJ9WNpQg==":"481-4814672_gems-world-academy-gems-world-academy-dubai-logo-2-240x94.png","VTaaT298FAVB9Z9zSEjy8Q==":"mbr-466x628.png","RGpuV6zD9Guj4lMTQ9Qi8Q==":"books-466x304.jpeg","NNEB3I4Ny3Jp2/ybfmqvSA==":"mbr-466x401.jpg","GVpVLVxCK+pmzVgtpun6Vg==":"mbr-466x301.jpg","weeW0L7TV3bSUlJwP8QLzw==":"books-1-466x304.jpeg","wQAjLtXmdqKxse9c/+D5JQ==":"mbr-240x205.jpg","90A+Sjn/Ya8h8ck9DPfdrg==":"mbr-240x195.jpg","CAE2a54wcSFy+rFNECKh7w==":"mbr-1-240x196.png","fOBsEV+V3uaNHkJrc+b8aA==":"mbr-2-265x192.png","EpuPQc1ngtAekmVmV8dGzg==":"background4.jpg","VDmzEsKlqjLZwzBqh/Nr3A==":"2020-07-27-1080x608.png","wPno8w5+C74SAfWvzNW8IA==":"mbr-1920x1480.png","UjbtBbchUp1n4oHAA+v6mg==":"mbr-1920x1279.jpg","r/BXMeohj5s36prk3QmE/w==":"mbr-1920x1371.jpg","qqgKgb41Euu24nF35DPTzg==":"mbr-1920x1274.jpg","r8S+XYWzPErldJdy1eYluA==":"mbr-1920x1372.jpg","BbFBL7WtgjdefAtBSrxz+A==":"mbr-446x738.png","Tj0G5KMg7NXR0bYI7SbYDA==":"mbr-1-446x738.png","wymapJia2G8YsUr2qo2yBQ==":"mbr-2-446x738.png","B04KphxrN6oLVswqgj4AQw==":"arabian-1456184-1280-446x424.png","b2gRes3etqMVVz397aUkuw==":"arabian-1456184-1281-446x424.png","Lb8m7PzjniIHqZPZJtU5Kw==":"arabian-1456184-1282-446x424.png","0+gncAneMJrUlJgjxbkFxw==":"male-1566592-1920-446x671.png","i/vFeYCzvk2kbskwYbxmsA==":"male-1566592-1921-446x671.png","Fh17E2LpDPA+FhbL+L3iOg==":"students-3836862-1920-374x264.png","g/73C2KNfdpe4Qv+LABR9w==":"students-3836862-1920-142x100.png","9ySc9z5FJKcetxtdK768gA==":"students-3836862-1921-374x264.png","nzKSg48oBwyj66r/9EXaVw==":"avatar-2191934-1280-374x210.png","L7QnLy4aGj+4DIJ0b259qg==":"book-2022464-1280-466x456.png","GHzWMTHodiQYSFX04CCuFg==":"training-3185170-1920-466x401.jpeg","fh8S3fRmwUH8p4aTtMtuMg==":"productivity-148197-1280-466x383.png","lZraGgrquvpeREtju/vsPw==":"productivity-148197-1281-466x383.png","CPxbUrxIvrwhHzkgAXE8Aw==":"avatar-2191918-1920-466x262.png","NCWdLZazOGvejcv5sFS69w==":"student%20mindset-705x1000.jpg","Wp2YXWTL0ZYygqwXFX27lQ==":"gcsemind-534x679.jpeg","w8pCDJ3VZh3/UU0eCeCXVA==":"32.jpg","tnKXsPi/mKLNc2oL/SSSPg==":"background1-1.jpg","4zgOa6wdi0gOyZqi68djFQ==":"mbr-1920x1280.jpg","xTPExaBuUhvvYqGnvX+erQ==":"mbr-1-1920x1279.jpg","xwegNtvP8s5Fy8bCcp5ygA==":"mbr-1920x1330.png","XET3Rfoq6AuJciYcXgoK/w==":"dashboard%20image-1314x531.png","6lb0jtiAe1Unz6uaWck/GQ==":"dashboard%20image-1314x531.png","VORNdEJnOSWE5ZhlepDPuw==":"annotation%202020-06-29%20225708-1124x521.png","7ZrZksmn8MnGaLsCvslDiw==":"report-560x705.png","yDts6/kfDHTP+VEkgdjeJg==":"mbr-1920x1275.jpg","5XRSEaxFxHEcJpe+eOJIdg==":"mbr-1-1920x1280.jpg","MYBPnn24Gc4TueewIMZj1Q==":"report-1-560x705.png","SCI8eqMvNYbIC6br+5iCjg==":"annotation%202020-06-29%20225708-638x296.png","7E5xBInOTFtC8EjwhAWg/A==":"annotation%202020-06-29%20225708-638x296.png","Ibgz1y91nr9ubt0q5HlCbA==":"report-638x803.png","dxSrMGPKrdisU9b/3GoYhQ==":"tutor%20report-638x404.png","vH2blIQG0ScHkOX0i4LMOQ==":"mbr-160x110.jpg","LAL8iAS4cCWiPyyuf4OPNw==":"purple%20brain-160x120.png","uhw4iP0NRZ3y9BdgByV5gg==":"brain-512x512.png","Iixt/Sxj1WSlYvBHQqS2Sg==":"mbr-1920x1080.jpg","+d3434tG+F+7dG1dNl3csA==":"mbr-1920x1081.jpg","h6Tme1ft++xNDiIhyK3GTQ==":"man-1459246-640-640x608.png","lTZR2qz9xC7mHARPHletlg==":"man-1459246-640-400x380.png","et4fTPty6c7sL3QulekVRQ==":"student-147783-640-387x640.png","hycIBL0IllXUY9U5uw7WeA==":"male-1566592_1920%20(1)-400x602.png","ZtTIJjS+/dLc3qs/vVuvBg==":"girl-3718537-1920-400x266.jpg","o8R6j7LERCfIiEND3zASCw==":"girl-3718522-1920-400x267.jpg","NWAnv8P1rTS8aG+u7PiMBQ==":"dc-240x245.png","Ing3eJ5IbgnJ6cgJFddATQ==":"ncc-225x225.png","uBJqfW+YaxGwTChV+ynJpw==":"cornwall-college-group-240x135.png","QVua+Xdley6h4nLYymfFQw==":"xcornwall-college-logo.png.pagespeed.ic.-lad7soghd-240x240.png","CCl7xOGXY9cDdTdV4/NvRw==":"onlylogo-240x281.jpg","bT+sPfWC8cye22/eYUwy/g==":"bkk-prep-icon-only-240x273.png","KNA9X7XYhmPQsFKPzwzEMA==":"mbr-2-1920x1280.jpg","3woP0TO7AedcHIC0f/n+Ng==":"brain-236x167.png","1wmRQkPqtnLgeqRZTYllcA==":"mbr-1920x1280.png","WysdFb/SfSELUekCks1QoA==":"mbr-3-1920x1280.jpg","ngCIU2ERXgmrfFLODwJzQA==":"mbr-4-1920x1280.jpg","/UbCkILb5yqAqiDYWHCGWQ==":"mbr-5-1920x1280.jpg","3e4SQ3B3OGyPi8vLXofslg==":"cathy-lewin-4-cropped-scaled-514x470.jpg","E8BfIfj+cpKGyXSQrc/Fgg==":"john-west-burnham-450x450.jpg","ajGp5owx3GEUm3ZBpQnQbQ==":"john-west-burnham-450x450.jpeg","mb8Dt2ldCHSpNymAzX6azg==":"cathy-lewin-4-cropped-scaled-514x470.jpeg","k2p3256IEabcfyqrliLY5Q==":"cloughy-514x771.jpeg","VMumF/G1g+sQrxiYBz1wSQ==":"cathy_photo_bw-500x685.jpeg","bupgWxNaC71uEDh55Nz5fA==":"background5.jpg","NDB1NtvXjMLhbYeUeyqtlw==":"john-west-burnham-1-450x450.jpeg","mChiiBbaDRf55T5hgqcnkQ==":"cloughy-724x1086.jpeg","nNZ5dXXLZGNdM1DP2tZVAw==":"face5.jpg","nqoLG54IEnZWVPGjN4arrg==":"face6.jpg","PLs0fqyltScpyYj96TuLwg==":"smaller-388x292.png","V1zkqDXtXd4f1DkzcMHspQ==":"smallerblue-388x292.png","zNhSjFsGwqYleY8mrM+WeA==":"book-2022464-1280-466x456.png","4xMr6g7J1LS7QJZrH1zbZw==":"book-2022464-1281-466x456.png","3/xVZdJO3N6LfojkVQLNoQ==":"book-2022464-640-495x484.png","eS1Bt8ymv8Kmge7Y3Qrf+w==":"book-2022464.svg","ZnoS+1e6xJtTNzZ4jZOmxA==":"book-2022464.png","4cR7mK4xU7vD3JbEs99o7g==":"book-2282303-1280-495x495.png","xN4dDMFzqADPU/yu9orNaQ==":"book-2282303-1281-495x495.png","oVkBR+dblJ139W1WA2L0cQ==":"student%20mindset-705x1000.jpg","IcpeT1rfvx0ADa7sJKkHzw==":"mbr-240x195.jpg","CE9t0/VDZMlo5pmFDd2bcw==":"avatar-2191918-1920-466x262.png","k/vJ5tR6+4YV04eRpAZN6g==":"cloughy-1-514x771.jpeg","rTPCLzYq02SbZxDLIDZrmA==":"cathy_photo_bw-1-500x685.jpeg","3uO1z1+GmAivGUbSeT4jug==":"john-west-burnham-2-450x450.jpeg","tkq88FBTFHxoNnwua0tZZg==":"mbr-1920x1280.jpg","vrP6YdvyWDWXzccfZrfM/g==":"face5-1.jpg","AngUSd8Som0ogD0oqznfTA==":"face6-1.jpg","3q8dGQxPaZ+L2TANQ4HinA==":"face8.jpg","DLe1usAYt1mea7M+8KHAKw==":"background1-2.jpg","JLWycCoU2y3+jv/PUMS9Sw==":"purple%20brain-936x702.png","+A6E5neGKkSdBJsco9lstw==":"mbr-1080x1027.png","LDTv5kb7pxL3r7YUquXKAQ==":"mbr-1080x720.jpg","RIDiyO5CRxkS0BN1j3EmTg==":"report-638x803.png","uUm7bK3qiPDlSo8lCJGNqw==":"sturpt-317x399.png","/kUHtaFEftdqx+bLaJh6bA==":"report-679x855.png","4Xgf3WdzcZPMyB1SJYHV1g==":"report-1-679x855.png","0ODwzNwNyMN3QDT0JCIJmA==":"tutor%20report-679x429.png","v1310Mxb+YMrgoJK2iw+Vg==":"tutor%20report-679x429.png","AcIQnaD7s+AxPOvhyclUaQ==":"tutor%20report-679x429.png","5aJfNuzGoA/4e2G/SlFufQ==":"tutor%20report-270x171.jpeg","nefdC6UVIbEwFjaVyG4mtA==":"tutor%20report-679x429.png","4BcJPvasQWf/oB5iz6uAFQ==":"mbr-1920x1330.png","QRzmBVPlY2GOEh2nBM9UXg==":"mbr-1-1920x1280.jpg","XrmdRStov/Wh4WbraTWu6A==":"alevel%20workbook-299x374.png","uh6uJBajlNPr7sysxNIHDA==":"mbr-679x721.png","LIlVEdV6wt/6JbFFt1Ic+g==":"mbr-679x679.jpg","a2YK8SSGMhLF0AIzTDA1eQ==":"mbr-679x382.png","Q2CaNSskhYBy2o1K7eASgw==":"mbr-1044x696.jpg","8uPRLwG3Nxf27Gd8wrkBPg==":"mbr-1-1044x696.jpg","iZ+ooCC7M0/wX3eZSGLjaw==":"mbr-1080x999.png","Gqz2PUh+yQPeUthmTwm++w==":"background7.jpg","9ztQQC4oOhvjb4cILM6mgw==":"annotation%202020-06-29%20225708-1080x501.png","F3sDEItQenULM2LvUNYqTA==":"tutor%20report-679x429.png","Q+6fdUZrI5CFNuuVB2G9JA==":"report-2-679x855.png","hRPOxOEowbGJ4M2zam/eIg==":"report-3-679x855.png","N+xkM7k3mluW76D7onWmDg==":"report-699x880.png","+ECB0rUnvifrw7CRcS8X/Q==":"report-1-699x880.png","BlbUBI49dkQ0dH8J4gpO1Q==":"report-2-699x880.png","tUnivALmwgYiIOFliY7zWg==":"report-3-699x880.png","foM/ramQab1sKLZSQxHyBQ==":"report-4-699x880.png","xG1MRnkq7qV4f61UW81VrQ==":"tutor%20report-699x442.png","e0fpQ1cFm6n41ZVJNxljIA==":"tutor%20report-699x442.png","A4L+bFhx3IwH5noofeWI0g==":"tutor%20report-699x442.png","GL4BSolPF+GCGJQcz1p4BQ==":"tutor%20report-699x442.png","C/QYSCfkjv10Ds06sDa8ZQ==":"report-5-699x880.png","f6yOE60itHE25MtcHC1MaQ==":"report-6-699x880.png","kl798UUL3wi+JrzAS1CxPg==":"report-7-699x880.png","uJO82peVvWpiLiqLdGT+gA==":"report-8-699x880.png","WjNP6k9BWLFy6HiS7qWbvA==":"report-9-699x880.png","0laZF0IplFznkZuZmGT2GQ==":"tutor%20report-699x442.png","CWPA9IlJdLzATeWV/6VYjA==":"report-10-699x880.png","66nVKeA1eygDt5DtaBKxIw==":"reportcrop-647x646.png","yfWSglhYqIQ3ayqlcLumKA==":"reportcrop-647x548.png","K3WqH+lAlascOygdJbVr5g==":"tutorreportcrop-582x451.png","khTnw4EsZs53Zy9f/FdFeQ==":"tutorreportcrop-679x546.png","iUTu5O+2pZUU2mgWMEm0cg==":"tutorreportcrop-662x497.png","QnAutFNNHrFQu/MRvWuyag==":"tutorreportcrop-605x382.png","ZPMdmzdIhiUY761y5P8oLg==":"tutorreportcrop-470x387.png","J238z/txaNQIUPJDDbB+GQ==":"bigbrain-1024x768.png","IMBS/RATtNv/wRwUYE8ztg==":"purple%20brain-1024x768.png","Re+wF4TuPXwgYUgn+ooAVQ==":"interactive-board-310636-1280-1080x851.png","JCXcVo0b3i79IcL+y0yZjw==":"natasha-kasim-bqd0id4qemc-unsplash-300x450.jpeg","Ri4ZG99DpXsE9NKdUfHlIQ==":"natasha-kasim-bqd0id4qemc-unsplash-1-300x450.jpeg","Ekx7nWjS9Gewh9naYRrV1g==":"yingchou-han-ijriecs3d4g-unsplash-300x200.jpeg","VoH5ZKTNsbaV4dO/+hm12Q==":"yingchou-han-ijriecs3d4g-unsplash-1-300x200.jpeg","NgsuJeWQsbr1xO4/Z8tmJA==":"dries-augustyns-jgg371o5y0w-unsplash-300x200.jpeg","sVbc04Np0J9uCu5fZSndOw==":"mbr-2-1920x1280.jpg","tlOhXHRFi+jW+sGrrKT5Gg==":"mbr-236x167.png","AO/zs55pRWp43qyYfTIF+A==":"stumind-534x757.jpg","tU96MsuuUgvX8A0KcBjTxw==":"overcoming-2127669-1920-923x410.png","yr6aVuZiGz6SGrXfXfjY9A==":"overcoming-2127669-1921-923x410.png","LWpVcpYp3hqP9ZxzjzhQQA==":"bps-923x519.jpg","8DNExEA0iApoGbvCMDRYeQ==":"welsh-500x375.png","dAjediHmkTanVhOU6my1HQ==":"bps-logo1-555x278.png","VtO/HCbB9f9ZinTjpCmFIQ==":"british-psychological-society-logo-500x333.jpg","INRYfh36ElmR4KfCKpfIvw==":"british-psychological-society-logo-500x333.jpeg","QwBEmHAYadI26rdPaoZ6Tw==":"british-psychological-society-logo-1-500x333.jpeg","SxoKpN9pvbr0LQyURDshoQ==":"circler-314x314.png","R5u6BdAz/KzbHJgzRv58VA==":"download-201x251.jpg","4k0/7bNT1dLj+WQ6ucx5jQ==":"webp.net-resizeimage%20(1)-121x151.png","dgmUW/e1xEe1buPDWqOFbw==":"webp.net-resizeimage%20(2)-40x50.png","sQxX71IMluddkhrs9RHZiQ==":"webp.net-resizeimage-201x251.jpg","AycSnl1iwDcjVsNVn6nLBQ==":"webp.net-resizeimage%20(1)-201x251.jpg","t2XZ6zpY53JyZWWPf1GMxg==":"background1-3.jpg","7phWZWZ3ncmHNNTuluyWEg==":"webp.net-resizeimage%20(2)-250x251.jpg","6Y6ZvNSrqoILbS9lh1RuGA==":"cropped-logo.gif","fNOqmsMFXAq57gYw3uh6Ug==":"webp.net-resizeimage%20(4)-201x251.png","LI56Ucd9zEVqSKqR8DXIUQ==":"webp.net-resizeimage.gif","XCFdvyyA7L1OxTVEHI7epg==":"british-psychological-society-logo-402x268.jpg","xaLICU4NeTuLLgHam5taOg==":"mbr-936x936.png","YAKH6+OYdmhwz6C8aTThUg==":"square-martin-griffin-1-360x360.jpg","oxQrW8VnQb7dhjNfcRz1xQ==":"tony%20480x480-520x520.jpg","lGNHXC9LuzarkQ/iCXWRhA==":"steveoakes-1-480x480.png","vWWC72EJOhbgG6w+8H3Y3Q==":"me%20website-699x638.jpg","y4ZTRfaBKyb27KBOIdflqQ==":"webp.net-resizeimage%20(4)-480x480.jpg","W+nGGAP1IPxjSHVD956Wgw==":"dc-240x245.png","CTRBfzfZeweeuplR42yVTg==":"belfast_metropolitan_college_logo-240x240.jpeg","Bha8qkomPZiAuIONviwQhA==":"ark-walworth-academy-southwark-london-240x240.jpg","IY6Ifwe8nL4EZTFvp4B97w==":"ncc-225x225.png","86gjnrC1Rr62+FdJAFMBxg==":"xcornwall-college-logo.png.pagespeed.ic.-lad7soghd-240x240.png","ayZyK2DCl4XmFg+nojNbFg==":"bkk-prep-icon-only-240x273.png","LDVKmYyrWKihNGYPg0OJpA==":"22spalding-205x197.png","CTWsZ60fGifukUldRsyA+A==":"shrewsbury-full-logo-01-1-1200x717.jpg","RVlAPRqOOgsTZagAyOv2lg==":"webp.net-resizeimage%20(5)-265x257.jpg","emoRhDpHmunt0N+ApRFqZg==":"aldar-academies-al-yasmina-academy-abu-dhabi-uae%20(1)-350x350.jpg","2SwFs8WmiPvo3+6JyqF+Ug==":"_sixthform_no_bg_high_resolution.gif","jN+rcPa3bdlDJzuBlwdKeQ==":"1200px-shsg_coat_of_arms.svg%20(1)-1200x1623.png","5lyss6SG+Eka+h+k3+ZsvA==":"webp.net-resizeimage%20(6)-360x360.jpg","Y1VEENelOS/WCkJBk+Z0zA==":"webp.net-resizeimage%20(5)-360x360.png","Vs+99LfhLwDcpfC0fm0UWA==":"webp.net-resizeimage%20(7)-300x300.jpg","qI/J8RJbSRE7JI1MaefiMA==":"aldar-academies-al-yasmina-academy-abu-dhabi-uae%20(1)-240x240.jpg","jvv+rNqm93Ro2ZwYoMrBKA==":"webp.net-resizeimage%20(5)-240x233.jpg","iIPC+JAspI/ygNMffDHJGw==":"1200px-shsg_coat_of_arms.svg%20(1)-240x325.png","GF5ibePEaV3j5gfoBkYd6w==":"_cuq-cnq_400x400-240x240.jpg","zTfbZAJ+jXkaYpeC5pnhqA==":"markham-240x240.png","qHLKl2pUYK2TZwYOJPiavQ==":"doha%20college-240x131.png","qVS27mBxePbzW67bvEdUsw==":"webp.net-resizeimage%20(8)-50x50.jpg","Arv82GO1PHbtJScvHGciig==":"webp.net-resizeimage%20(9)-100x100.jpg","SSn9AJomI9r86CsVp3denw==":"webp.net-resizeimage%20(9)-150x150.jpg","m1+4lPcuwPf7o6c0EVIm7w==":"webp.net-resizeimage%20(10)-100x100.jpg","68g6PVpZJsGcYbDIQsgYCA==":"webp.net-resizeimage%20(11)-100x100.jpg","6NPgRkcg6OIoqJt9hIVr7A==":"webp.net-resizeimage%20(6)-100x100.png","jqd7oA0E5Bgy9paD7Pv2sg==":"webp.net-resizeimage%20(7)-100x100.png","rZlzTcBt+IU78csYojEBaQ==":"webp.net-resizeimage%20(8)-100x100.png","ZkGFh7CFFxN3EeHXIB72Wg==":"webp.net-resizeimage%20(9)-150x150.png","VtdGAjOKKAWRBY7SYPdN4Q==":"webp.net-resizeimage%20(12)-150x150.jpg","3oe1AH55X4GmXZVIPIzvgQ==":"webp.net-resizeimage%20(11)-150x150.png","Jovz/R/s8BdW1pxezMtvbg==":"webp.net-resizeimage%20(12)-150x150.png","NsyalSOkFZ88f3+NsFGd0A==":"bolton_school_foundation_joint_logo-240x240.jpg","r6B+P15xwKoiM8Wdntbvyw==":"xcornwall-college-logo.png.pagespeed.ic.-lad7soghd-480x480.png","Itkxaoop1nREsTpgG3SIZA==":"dubai%20british-512x512.png","LYifliY3mwNpyrA46ig9aA==":"nptc-400x400.jpg","PVJaFT31ycM+YO0d/TH4mA==":"markham-475x475.png","Hqt3/ttPaoxAbMPkLBYl+g==":"col-boys-225x225.png","AuKzybi0O+y+olWrbBqNCw==":"doha%20college-542x296.png","Kss50HYKf3s0HqPxEaVxCg==":"carres-400x400.jpg","soym8sm9y1MicyzMNvi3Sg==":"_cuq-cnq_400x400-400x400.jpg","BqkrMQn/G5+yySejjTYhzw==":"immanuel_college_logo-316x316.jpg","Fv9juArqoHISBOMiLeplKQ==":"clip-200x200.jpg","khftX2N660mmE2/R47C6Ag==":"mmu-logo-scaled-2560x1914.jpg","g/SBcEMlsURSnWZjv0n3pg==":"princethorpe_square-360x360.jpg","qnLWMUVZQGbG3MsLIXIeMA==":"hartpury-400x400.jpg","pYx2lt5IF9i+/3CCyrvV+w==":"pingle-400x400.jpg","l+RbLC+6FB5lIFcOGAhSmA==":"barnard-512x370.jpg","OZ3v6/D8V9IleXH4ONNrmg==":"ecole%20mondiale-902x841.png","DdJR2w8BE3wISpG3kcy/LQ==":"_cuq-cnq_400x400-150x150.jpg","RZ1/wt6aWntFQdFREXCpmA==":"_sixthform_no_bg_high_resolution%20copy-150x150.png","ol+N5ms9ueYBKWkDvsEy+Q==":"1200px-shsg_coat_of_arms.svg%20(1)%20copy-150x203.png","cOe+237vw20efCw8R9YPZA==":"1871_blanchelandecollege%20copy-150x75.png","wgOQT5iSyymDWepABsa4Qw==":"aberaeron%20copy-150x150.png","UaA6/Tl56OYkS9RX1RirzA==":"aldar-academies-al-yasmina-academy-abu-dhabi-uae%20(1)%20copy-150x150.png","pY63p+9MIYUezn/n1XnnPg==":"barnard%20copy-150x108.png","sEQWzjJGJLfHq37rAT5eIQ==":"bolton_school_foundation_joint_logo%20copy-150x150.png","+DGH4GdCswZsNnMN95CwJg==":"carres%20copy-150x150.png","W7imjMT5GSvIUzfE3e6gmQ==":"clip%20copy-150x150.png","zdFkMlvGy+H2fHKlmr2kIQ==":"col-boys%20copy-150x150.png","XzSgFIKbx8IECr57DTAV9A==":"doha%20college%20copy-150x82.png","O9uE07hKl4fw+AmqNGySig==":"dubai%20british%20copy-150x150.png","OSjH9QnWar/AJg3Z20iOcQ==":"durham-school-2%20copy-150x58.png","LrmB5CRJlGDNaq7RRzcX3g==":"ecole%20mondiale%20copy-150x140.png","4Qxi2HFdO10DfIPE/jIUQA==":"hartpury%20copy-150x150.png","diQahFW6aTOMvL+wI6fvBQ==":"immanuel_college_logo%20copy-150x150.png","qowNFEFooese210yB7MJIw==":"kings-school-dubai-uae%20copy-150x150.png","XTvCU/rVCJYiJ27RmlaXUg==":"kshs%20copy-150x177.png","IiIMQHoVWVXDIFDcYIZXDA==":"loreto%20copy-150x113.png","ZIqLCOGEuIfpsTzaZsMdNQ==":"markham%20copy-150x150.png","tEQABWHRITXb6gcutUMz6Q==":"marklham%20copy-150x181.png","EzpMujkHuAQFYkIRRRW9zg==":"mmu-logo-scaled%20copy-150x112.png","xmc1eE/ouRT9rdSGBvvyjw==":"nptc%20copy-150x150.png","krsAa54pEgeFYdCrGIeg9g==":"bkk-prep-icon-only-253x288.png","GVwnNBBrqcrmhaH4ctMlyw==":"webp.net-resizeimage%20(7)%20copy-150x150.png","DX4/6RXK8blCbgtjicQQcQ==":"xcornwall-college-logo.png.pagespeed.ic.-lad7soghd-253x253.png","9SuQEK+jNmm8klKSFSs36A==":"ncc-1-225x225.png","RWSkT3Vh+9xg1WNnBdi0FQ==":"dc-253x258.png","vfTZr2ri33SfKr7GOioBGw==":"student%20mindset-466x661.jpg","UhcjIxmHQuT0SOafUwfK8w==":"microphone-704255-1920-466x311.jpg","mBMS2208BEZyQMxwlHiSyQ==":"annotation%202020-08-31%20201759-466x262.png","oc8Rm+THL/yyITBwMn6ZOw==":"statistics-2899893-1920-466x311.jpg","uoEmJcFfk/EfujTl9RBvRA==":"event-1597531-1920-699x465.jpg","VdkDt2qWUZNUla4qtakCsA==":"dylan-gillis-kdeqa3atnby-unsplash-699x466.jpg","Ptn4h30hGYWjJFnS36rYSA==":"workplace-1245776-1920-699x466.jpg","ChfKs2C4iehT9N3bNMkSBw==":"brain-236x167.png","5YEaBIV1KtSFrqWu+lHuew==":"dc-1-240x245.png","ijzi9C/ca+MxGc3W2OvHOQ==":"dc-150x153.png","hc+t9ADv3sR9YyDT+h05sQ==":"cloughy-1-200x200.jpg","lG4ZBOQ1KYOpZ2EafAN2/A==":"john-west-burnham-2-200x200.jpg","8L14xv8hJaF2XKkZ7XagLA==":"cathy-photo-bw-1-200x200.jpg","OJaDmGYefb3Ui16MSfkKJg==":"bigbrain-466x350.png","2zX8Gd3sA9HwxYUlvhqQ8A==":"background2.jpg","6QBAXFuLzvM2SWejWH/Ltw==":"02.png","4mV5vhSy70ejESJFYw8lbQ==":"background8.jpg","ksSl/M7qiF9SMeX5hJf/2g==":"2021-01-10%20(3)-738x360.png","rmvzGVWIEpJzaQKoQk2wpA==":"dashboard-738x665.png","iuo7pYbrRwe4kCfoz9n6Gw==":"bar%20chart-738x666.png","lHpWCYUQwblRSEz77z038g==":"annotation%202020-06-29%20225708-738x683.png","SAGeI12tEBYxrQJ8K1TGxw==":"2021-01-11%20(11)-1459x766.png","2PVnJsmkudoCEKKNzRlcGQ==":"myvespa-1280x1052.jpg","6xf3ryLS7YDP1o5C+WgMPw==":"mbr-1459x730.png","ZrOjsRe6GKJ1wCs0HF14+Q==":"myvespa-1080x888.jpg","gg3huI0yVj13vYlQE5ngNg==":"bar%20chart-1002x904.png","hsv6HRUx3dFuESoAGkWmHQ==":"monitor-32743-1280-1080x888.jpg","NF1KyXYaZVQjaMbXHV1+bA==":"monitor-32743_1280%20(1)-320x263.jpg","lEpfVvvMcbNx5wWBi0Na2w==":"image-936x702.png","0J3rE1ITzRhxZ1doGxP8GQ==":"pngegg%20(4)-936x702.png","KM4f3NIC4Rdm6poHX3zJRQ==":"pngegg%20(1)-936x702.png","A8yXDRVbuhKFYOZIsRWqeA==":"pricing%20-2800x1318.png","QEBOCr0Q0o44I31/4atiOA==":"image-536x402.png","XjrzsJ64nR9rPxo69uNkRw==":"pngegg%20(2)-536x402.png","gC4Iz17pRedEIbKCLVoXgQ==":"customcolor_logo_customcolor_background-171x103.png","g5CFoxbsOX4pKO2UFYZzzA==":"black_logo_transparent_background-201x121.png","oX6aYeQm3VuqN3Q0gW+x+A==":"customcolor_logo_customcolor_background-201x121.png","A/GlW272kLx0rTRc2en92g==":"full_margin_transparent_customcolor-201x121.png","wwiHm4w2Ssui0K/UKW+9Ug==":"full_trimmed_transparent_base-1465x1667.png","6BmLNrxqzPBqOSMqG7F22w==":"full_trimmed_transparent_base-425x484.png","CsaxKvj1vfbO2uBlUJX5ig==":"full_trimmed_transparent_customcolor-118x134.png","pzrvIc74S8iDNI5VyeYd1Q==":"full_trimmed_transparent_customcolor-1465x1667.png","xzQ3R9VDwiIEH8BfAeJQOQ==":"full_trimmed_transparent_base-700x797.png","+QiobyCMxuejwWaDq5ztcA==":"white_logo_dark_background-118x71.png","NtPRP924m/l2NRpoKJYFkg==":"full_trimmed_transparent_white-223x254.png","w49jRns0pZeKGFhjWeIugg==":"icon_trimmed_transparent_customcolor-106x115.png","S4Gndee3YkV8fLnBty9eGg==":"customcolor_logo_transparent_background-2846x1708.png","mI66AXmFmzdzBnV7wq+MWw==":"customcolor_logo_transparent_background-832x499.png","JLQ+vRuMwIM9HqdTWUNQDw==":"full_trimmed_transparent_customcolor%20(1)-832x947.png","kJOlF4SbVodnEBFcZXA05w==":"mbr-1000x667.jpg","otX6t1RM8NYziiFAiKvB+g==":"mbr-1032x534.png","8kvhoEKWw7ExSurrgqD3Vg==":"mbr-1-1032x534.png","3lBuISBoHwriORmdARAlew==":"mbr-1-1920x1280.jpg","fIhtdDjoXpP4lmJFWI/DHA==":"mbr-1920x1279.jpg","eEVJhkjuBvj2TSgjhFwzNA==":"mbr-2-1920x1279.jpg","uGyBKURGxoNPwhE5+sxWBQ==":"mbr-1920x1277.jpg","2kvUQ+S0liRprl1Ydfpb0g==":"mbr-1920x1080.jpg","rrlWtJkAhQ0Ygmba6n+16A==":"pexels-burak-kostak-18809-2000x1333.jpg","uA5LgVuz2dIgDa0/7wS/UA==":"pexels-alexander-krivitskiy-1156546-2000x2013.jpg","DHOfHyelp047CW6YKtKRlA==":"pexels-subin-946727-2000x1330.jpg","iBABvbXucQ9BClvsiv9OKQ==":"pexels-mathias-pr-reding-4385860-2000x1333.jpg","beWBsfaRphRpl8LzsGL6lA==":"pexels-pixabay-357514-2000x1333.jpg","eOueXM1BQEVUSp4uWAJ+4w==":"pexels-pixabay-414565-2000x1334.jpg","8Ihu3QipZ7r1yV9/DNZwUw==":"pexels-pixabay-261579-2000x1500.jpg","ZqeVZXtb6qywjafJCYTQjQ==":"pexels-donald-tong-193821-2000x1333.jpg","qgOzlv1EkFVkg+jpPJ9pag==":"pexels-afrika-ufundi-1406547-2000x1333.jpg","YmbsSDv/tsfM0S3RHa7Awg==":"full-trimmed-transparent-customcolor-1-128x146_2.png","u8IC/XeMZR+MF91VWRiMCQ==":"background18.jpg","6B77TZl2I8pH/FuHSEIFbQ==":"full-trimmed-transparent-customcolor-1-512x512.png","LHQlUVbLGmgwwGXv8KqATQ==":"customcolor_icon_transparent_background-96x69.png","zUsoZqCw57JGDGDBe8kKXA==":"pexels-lukas-669621-2000x1325.jpg","mq0JkBQkiBJBy9tSv4oDBw==":"pexels-nitin-arya-1029141-2000x1333.jpg","y/DLmzGbW9iPufkPWiDdAQ==":"pexels-fauxels-3184317-2000x1333.jpg","AEeTanOzkFaIZt6SBC4y7w==":"mbr-1920x1272.jpg","lAAZjbuJmZEyw14BFmhOjA==":"pexels-diva-plavalaguna-6150527-2000x1333.jpg","s3IVk6sojYDJisb0F+IEog==":"mbr-1-1920x1279.jpg","fA9QNxq5CZqTiYXnW15qBQ==":"customcolor_logo_transparent_background-756x454.png","DrmiLx4mr4Y0PWE8dGqoGw==":"petroc%20college%20of%20further%20&%20higher%20education-283x142.png","f1ZQ7DVINol+98C8D/8G7Q==":"promogif.gif","6tPoD+f3eEDe3ppNQRv3Zg==":"vespa-academy-promo_842x421-748x421.jpg","csiE+0TZoVjYizUgWmf/QQ==":"pexels-stanley-morales-1454360-2000x1333.jpg","S5T3FZuK4Td+5OgQDsV55A==":"jaime-lopes-0rdboadnbwm-unsplash-700x467.jpg","SR292kYo7b4uhs9WqHEx2A==":"matese-fields-pvhma684eei-unsplash-700x465.jpg","LQrMQl5yWo87kDLoc/i5tw==":"sincerely-media-dgxogexaxm8-unsplash-700x467.jpg","89b/pKTaDUgI9OlQos+KQw==":"edwin-andrade-4v1dc_eocwg-unsplash-700x555.jpg","idnZdNM0lmIJBn+AGVu5xw==":"edwin-andrade-4v1dc_eocwg-unsplash-700x555.jpeg","JP0SjepwxhUAN3g4JEO0Lw==":"tonyrefail-community-school-logo-final-png-860x779.png","rt0hlAU49eW6/A9AqNjS+w==":"png-transparent-industrial-and-organizational-psychology-psychologist-british-psychological-society-health-psychology-ruling-minds-psychology-in-the-british-empire-blue-text-hand_adobe_express-764x491.jpg","AnYO4QbC1ppP8vTtkX9/9A==":"0008123_the-gcse-mindset-student-workbook-550-389x550.jpg","4azU+H7bnR8RDeYMoa73dg==":"0008123_the-gcse-mindset-student-workbook-550-389x550.jpeg","+s1xnHQ2HKHf5o4xHIIDnA==":"monitor-32743-1280-578x475.jpg","TyeR3UXUVtcZcyjXHZNyMA==":"new%20vespa%20book-342x440.jpg","UWOFyqiIT1JeQN3ICgUonw==":"handbook-855x1099.jpg","ags+OLuXJ1nhj8Hqc0b96A==":"alevelmind-389x500.jpg","NzmGXDpEdBGJ9Ck83U77qw==":"gcsemind-534x679.jpg","EzN2VvCPf47ACQovHI4uig==":"0008123_the-gcse-mindset-student-workbook-551-389x550.jpeg","3ZD0bx5C3g4P4TB5gSVajg==":"alevel-workbook-1-299x374.png","0Nqm+Z+k+iACe8hXlSCWTQ==":"img-20240429-wa0000-1125x618.jpg","FC1m7KFByaziuViQz85Wgg==":"background1-1.jpg","OTko6KwXe4bRifNEF7RH9g==":"lcgstutorbadge-500x500.png","GueJFqGjd1msG+iDrHsQEg==":"b00c881e-ce82-4a9a-8efe-9b388f70ea77_medium-384x384.jpg","K1gp9ZnTCK/mrx59aQ17NQ==":"csc%20logo%20rgb-1249x625.jpg","Aj4GNGA3gvIl4HCdTyHusQ==":"top_grades_by_country-1024x673.png","xoOo96IZPXXiUxSKRczF3g==":"csc%20logo%20rgb-2362x1182.jpg","zoGB1BOxCRHcBMmIrJNmNQ==":"9nlkidya_400x400-399x399.jpg","mu4BSkjTHaQeNySTi45GDg==":"slggmb5q_400x400-272x272.jpg","dXX1ValNKyWfvGHng74BzQ==":"university-of-pretoria-logo-south-africa-350x350.jpg","oQf7kOY6qCVvlWEKJlwZyw==":"university_of_pretoria_coat_of_arms%20(2)-1200x1897.png","T2hj3qfGEjWFlaIzfrOUVw==":"untitled%20(53)-1080x1080.png","9RCyaOcXdkzxZ79yKl/ilg==":"hartpury-uni-and-college-logo-1200x630.jpg","wx6H///GAe4cnYpy119v8w==":"nptcg-coll-cmyk-facebook-1024x512.jpg","kxnM+aMjo7i8lPiQVZY+nQ==":"logo%20(1)-418x427.png","ESkeqLVItWlsqlIRRibaqw==":"img-20241114-wa0000-949x1396.jpg","IZxRCJK/UGxiqRDEgJhtpQ==":"teach%20secondary%20awards-949x599.jpg","3flZ/jGAsQyn9h7yMGjNhA==":"teach%20secondary%20awards-949x599.jpeg","ncLO/PEIOEj5Lfjo4qdEmg==":"cpd%20winners-532x335.jpg","9ajlzfJSooo42t2GCSlLiQ==":"cpd%20winners-600x377.jpg","ETb+qfk1C3apwFxOym5Ceg==":"pexels-pixabay-53594-2000x1500.jpg","IVqwRMWNztvMBZVTWxbCGQ==":"pexels-pixabay-53594-2000x1107.jpg","E9vZb3MQkIq3nbL0XoS8sA==":"pexels-stanley-morales-1454360-2000x1333.webp","+3exDJtDXP2p3gKkz2SF9Q==":"pexels-diva-plavalaguna-6150527-2000x1333.webp","1OyPfQcAdXCihjQ3SsPeMQ==":"pexels-diva-plavalaguna-6150528-2000x1333.webp","FqNQ6ouB2QZfjFBxbl5Mxw==":"pexels-pixabay-265087-1920x1280.jpg","tMk1L8UQGwxoPfTqdJMzdg==":"pexels-enginakyurt-3339712-1920x1280.jpg","OSsaCBA2DslqwIQu3z9hzg==":"pexels-olly-3784324-2000x1333.jpg","vt9QNfVcQt0M7yZ42kRA9g==":"pexels-ketut-subiyanto-4126712-2000x1333.jpeg","YWbtlDUt+WLq5S/R6LfN+w==":"pexels-ketut-subiyanto-4126713-2000x1333.jpeg","3yOK9XaM3fpZsg743MB+Pw==":"pexels-ketut-subiyanto-4126714-2000x1333.jpeg","paCg91+IE7mS3/dLt7jaFw==":"matese-fields-pvhma684eei-unsplash-700x465.webp","j+h/OUEYG87a4NtZ/2Jp9Q==":"mbr-1920x1272.webp","CgY9enlpIncZrrh/dCjsRQ==":"untitled-1920x1272.png","a7SS3BtSJar4X0J5poEnwg==":"untitled-1-1920x1272.png","vvcL/0l0tdvVV2zSkjXAwA==":"untitled%20(2)-1920x1272.png","Fbo5dCNNGb1743ZBhysYTg==":"untitled%20(3)-1920x1272.png","xXRoVhdimuTubU1N1E2Faw==":"untitled%20(5)-1920x1080.png","HJMJSroZc7xZGgSG49LNnw==":"untitled%20(6)-1920x1080.png","sW4IkVLPFny6GAvpDAm/HQ==":"untitled%20(6)-1920x1080.png","3MTJ8dOGJLhHrrkFRaScTA==":"untitled%20(7)-1920x1080.png","HgztyLQ2v+Xxjrd6oYHkJQ==":"untitled%20(8)-1920x1080.png","VVs8aIakVtK2Ja5nvX0jXg==":"untitled%20(9)-1920x1080.png","2ESXvAvS4M1nDhkiOTMFnw==":"pexels-keira-burton-6147395-2000x1333.jpg","0xdmaICnrVsl2oZqcyoQcg==":"hd3d476abfbc54e228f11c1abae716f1e4.jpg_720x720q50-720x720.jpg","V+AvKT37U5bV/cZ8X9qipQ==":"h6d9a0f3b906d45ad8acc5019b54a2d73y.jpg_720x720q50-720x720.jpg","Qj6o/6fNWV7QX3+pla3gHQ==":"pexels-startup-stock-photos-7103-2000x1182.jpg","DPut+0D2HX97/KNhwAnMJQ==":"469510386-800x800.jpg"}